findlinear/__init__.py
findlinear/_example_data.py
findlinear/_models.py
findlinear/findlinear.py
findlinear-0.4.2.dist-info/METADATA
findlinear-0.4.2.dist-info/WHEEL
findlinear-0.4.2.dist-info/RECORD
