Metadata-Version: 2.1
Name: findlinear
Version: 0.4.2
Summary: To find the linear segment of a curve or dataset.
Home-page: https://findlinear.readthedocs.io
License: MIT
Keywords: linear segment,systems biology,bioinformatics,plate readers
Author: Yu Huo
Author-email: yu.huo@ed.ac.uk
Requires-Python: >=3.8,<3.11
Classifier: Intended Audience :: Science/Research
Classifier: License :: OSI Approved :: MIT License
Classifier: Operating System :: OS Independent
Classifier: Programming Language :: Python :: 3
Classifier: Programming Language :: Python :: 3.8
Classifier: Programming Language :: Python :: 3.9
Classifier: Programming Language :: Python :: 3.10
Classifier: Topic :: Scientific/Engineering :: Bio-Informatics
Requires-Dist: findpeaks (>=2.4,<3.0)
Requires-Dist: matplotlib (>=3.5.0,<4.0.0)
Requires-Dist: numpy (>=1.20.3,<2.0.0)
Requires-Dist: scipy (>=1.7.3,<2.0.0)
Requires-Dist: sympy (>=1.9,<2.0)
Project-URL: Documentation, https://findlinear.readthedocs.io
Project-URL: Repository, https://git.ecdf.ed.ac.uk/s1856140/findlinear
